<annotation>
	<folder>imageset_153</folder>
	<filename>sequences_euro_ball_robot_1_a_00057.png</filename>
	<path>/home/kenji/Documentos/Robo/imageset_153/sequences_euro_ball_robot_1_a_00057.png</path>
	<source>
		<database>Unknown</database>
	</source>
	<size>
		<width>800</width>
		<height>600</height>
		<depth>3</depth>
	</size>
	<segmented>0</segmented>
	<object>
		<name>1</name>
		<pose>Unspecified</pose>
		<truncated>0</truncated>
		<difficult>0</difficult>
		<bndbox>
			<xmin>487</xmin>
			<ymin>150</ymin>
			<xmax>544</xmax>
			<ymax>216</ymax>
		</bndbox>
	</object>
	<object>
		<name>1</name>
		<pose>Unspecified</pose>
		<truncated>0</truncated>
		<difficult>0</difficult>
		<bndbox>
			<xmin>588</xmin>
			<ymin>172</ymin>
			<xmax>728</xmax>
			<ymax>285</ymax>
		</bndbox>
	</object>
	<object>
		<name>1</name>
		<pose>Unspecified</pose>
		<truncated>0</truncated>
		<difficult>0</difficult>
		<bndbox>
			<xmin>563</xmin>
			<ymin>289</ymin>
			<xmax>695</xmax>
			<ymax>379</ymax>
		</bndbox>
	</object>
</annotation>
